Metadata-Version: 1.1
Name: ASCE
Version: 0.0.8
Summary: ASCE is a simple program that operates on matrices
Home-page: UNKNOWN
Author: CZB ASCE GROUP
Author-email: sandrine.sila@net.usj.edu.lb
License: MIT
Keywords: library
Platform: UNKNOWN
Classifier: Development Status :: 5 - Production/Stable
Classifier: Intended Audience :: Education
Classifier: Operating System :: Microsoft :: Windows :: Windows 10
Classifier: License :: OSI Approved :: MIT License
Classifier: Programming Language :: Python :: 3
